pinkyCGI.v
//
`define INST_END_INDEX	20

//common bit lengths
`define WORD 		[15:0]
`define OPCODE 		[15:11]
`define CC			[10:9]
`define IMM			[8]
`define DEST		[7:4]
`define	OP2			[3:0]
`define REGS		[15:0]
`define PC			registers[15]
`define SIZE		[65535:0]
`define PRESIZE		[11:0]
`define BASEOPS		[3:0]

//stage 
`define	STAGE       [1:0]		
`define STAGE0		0
`define STAGE1		1
`define	STAGE2		2
`define STAGE3		3

//OPCODES
`define OPADD 	5'b00000
`define OPADDF 	5'b00001
`define OPAND	5'b00010
`define OPBIC	5'b00011
`define OPEOR	5'b00100
`define OPFTOI  5'b00101
`define OPITOF  5'b00110
`define OPLDR   5'b00111
`define OPMOV   5'b01000
`define OPMUL   5'b01001
`define OPMULF  5'b01010
`define OPNEG   5'b01011
`define OPORR   5'b01100
`define OPRECF  5'b01101
`define OPSHA   5'b01110
`define OPSTR   5'b01111
`define OPSLT   5'b10000
`define OPSUB   5'b10001
`define OPSUBF  5'b10010
`define OPSYS   5'b10011
`define OPNOP   5'b10100
//5'b10101
//5'b10110
//5'b10111
`define OPPRE   5'b11000


//CC values
`define	AL			0
`define S 			1
`define NE			2
`define EQ			3

//OP2 MACRO
`define Op2struct(IR, PRE, PREFLAG, REGFILE) \
	(IR `IMM ? { PREFLAG ? {IR `OP2, PRE} : {12{IR[3]}}, IR `OP2 } : REGFILE[IR `OP2] )

module stage0(PCfollow,ir,halt,R15,Z,clk,reset);
			  
output reg `WORD PCfollow;
output `WORD ir;
output halt;
input `WORD R15;
input Z,clk,reset;

reg `WORD instmem `SIZE;	
reg `WORD PC;				
wire `WORD irInitial;
wire checkCodes;
wire [1:0] CC;

always@(reset) begin
	PC = 0;
	$readmemh("inst.txt", instmem, 0, `INST_END_INDEX);
end

always@(posedge clk) begin
	PCfollow <= PC;
	PC <= PC + 1;
end

assign irInitial = instmem[PC];
assign CC = irInitial `CC;
assign insertNOP = ((CC == `NE)&&(Z == 1))||((CC == `EQ)&&(Z == 0));
assign ir = (insertNOP == 1)? {`OPNOP,11'h000} : instmem[PC];
assign halt = (ir `OPCODE == `OPSYS);

endmodule


module stage1(pc_follow, pc_to_reg, ir_out, Rd_out, op2_out, ir, clk, reset, pc);
output reg `WORD pc_follow;
output `WORD Rd_out, op2_out;
output reg `WORD ir_out;
input `WORD ir, pc_to_reg;
input clk, reset;
input `WORD pc;

wire [4:0] op_code;
wire [1:0] cc;
wire immFlag;

reg preFlag;
reg `PRESIZE pre, pre_temp;



always@(reset)begin
    preFlag = 0;
    pre = 0;

end

//split up instruction word into the separate chunks
assign op_code = ir `OPCODE;
assign cc = ir `CC;
assign immFlag = ir `IMM;
assign Rd = ir `DEST;
assign Rd_out = PE.regfile[Rd];

//`define Op2struct(IR, PRE, PREFLAG, REGFILE) \
//	(IR `IMM ? { PREFLAG ? {PRE, IR `OP2} : {12{IR[3]}}, IR `OP2 } : REGFILE[IR `OP2] )
assign op2_out = (ir[15] & ir[14]) ? 16'h0000 :  `Op2struct(ir, pre, preFlag, PE.regfile);

//assign pre = pre_temp;
//assign pre = (ir[15] & ir[14]) ? ir `PRESIZE : pre_temp;
//assign preFlag = ir[15] & ir[14];
//assign Rn = ir `OP2;

always@(posedge clk)begin
    if(ir[15] & ir[14]) 
	begin
	preFlag = 1;
	pre = ir `PRESIZE;
	end
    else if(immFlag) preFlag = 0;
    
    pc_follow <= pc;
    ir_out <= ir;
    //Rd_out <= regfile[Rd];
    //op2_out <= (ir[15] & ir[14]) ? 16'h0000 :  `Op2struct(ir, pre, preFlag, regfile);
end
endmodule

module stage2(pc_follow, ir_out, value_out, ir_in, addr, data, clk, reset, pc);
output reg `WORD pc_follow;
output reg `WORD value_out;
output reg `WORD ir_out;
input `WORD addr, data, pc;
input clk, reset;
input `WORD ir_in;
reg `WORD datamem `SIZE;
reg `WORD addr_latch, data_latch;

wire [4:0]op;
assign op = ir_in `OPCODE;

//do the ALU thing
//when comparing to the PinKY instruction set
//Rd is addr and Op2 is data

always@(reset)begin
    //only reading in 16 data mem locations for now
    $readmemh("data.txt", datamem, 0, 15);
end


always@(posedge clk)begin
    case(op)
        `OPADD : begin  value_out = addr_latch + data_latch;end
        `OPAND : begin  value_out = addr_latch & data_latch;end
        `OPBIC : begin  value_out = addr_latch & ~data_latch;end
        `OPEOR : begin  value_out = addr_latch ^ data_latch;end
        `OPLDR : begin  value_out = datamem[data_latch];end
        `OPMOV : begin  value_out = data_latch;end
        `OPMUL : begin  value_out = addr_latch * data_latch;end
        `OPNEG : begin  value_out = -data_latch;end
        `OPORR : begin  value_out = addr_latch | data_latch;end
        `OPSHA : begin  value_out = (data_latch>0) ? addr_latch<<data_latch : addr_latch>>-data_latch;end
        `OPSTR : begin datamem[addr_latch] = data_latch; value_out = data_latch;end
        `OPSLT : begin  value_out = (addr_latch<data_latch);end
        `OPSUB : begin  value_out = addr_latch - data_latch;end
    //we'll catch these in the default case
    //    `OPSYS : begin ; end
    //    `OPNOP : begin ; end
    //    `OPPRE : begin ; end
        default : begin value_out = 16'h0000; end
    endcase
    data_latch <= data;
    addr_latch <= addr;
    pc_follow <= pc;
    ir_out <= ir_in;
end
endmodule

module stage3(pc_follow, z_reg, ir_in, result, clk, reset, pc);
input `WORD result, pc;
input `WORD ir_in;
input clk, reset;
output reg `WORD pc_follow;
output reg z_reg; //should this be a reg?

reg [4:0] opcode;
reg [1:0] cc;
wire z;
wire Rd;
reg dummy;

assign Rd = ir_in `DEST;

//assign z = (cc == `S) ? z : (((result == 16'h0000) & (cc == `S)) ? 1'b1 : 1'b0);

always@(reset)begin
    z_reg = 0;
end


always@(posedge clk)begin
    cc = ir_in `CC;
    opcode = ir_in `OPCODE;

    if (cc == `S)begin
	if (result == 16'h0000) z_reg = 1'b1;
	else z_reg = 1'b0;
    end
    
    case(opcode)
	//`OPSYS : begin dummy = 1; end
	//`OPPRE : begin dummy = 1; end
	`OPSYS : ;
	`OPPRE : ;
	`OPNOP : ;
	default: begin PE.regfile[Rd] = result; end
    endcase	
	
	
end
endmodule


module processor(halt, reset, clk);
output reg halt;
input reset, clk;

//the underscore<digit><digit> notation indicates control flow
//for example _12 means it goes from stage 1 to stage 2
wire `WORD PCfollow_01, PCfollow_12, PCfollow_23, PCs4_to_reg;
wire `WORD ir_01, ir_12, ir_23;
wire haltedP;
wire `WORD Rd_12, op2_12;
wire `WORD result;
wire z;
reg `WORD regfile `REGS;

always @(reset)begin
    $readmemh("regs.txt", regfile, 0, 15);
end

always @(posedge clk) begin
halt <= haltedP;
end

//module stage0(PCfollow,ir,halt,R15,Z,clk,reset);
stage0 s0(PCfollow_01,ir_01,haltedP,16'h0000,z,clk,reset);

//module stage1(pc_follow, pc_to_reg, ir_out, Rd_out, op2_out, ir, clk, reset, pc);
stage1 s1(PCfollow_12, PCs4_to_reg, ir_12, Rd_12, op2_12, ir_01, clk, reset, PCfollow_01);

//module stage2(pc_follow, ir_out, value_out, ir_in, addr, data, clk, reset, pc);
stage2 s2(PCfollow_23, ir_23, result, ir_12, Rd_12, op2_12, clk, reset, PCfollow_12);

//module stage3(pc_follow, z_reg, ir_in, result, clk, reset, pc);
stage3 s3(PCs4_to_reg, z, ir_23, result, clk, reset, PCfollow_23);

always @(reset) begin
	halt = 0;
end

endmodule

module testbench;
reg reset = 0;
reg clk = 0;
wire halted;
processor PE(halted, reset, clk);
initial begin
  $dumpfile("dumpfile.vcd");
  $dumpvars(0,PE);
  #10 reset = 1;
  #10 reset = 0;
  while (!halted) begin
    #10 clk = 1;
    #10 clk = 0;
  end
  $finish;
end
endmodule

dumpfile.vcd
$date
	Thu Nov  1 15:14:23 2018
$end
$version
	Icarus Verilog
$end
$timescale
	1s
$end
$scope module testbench $end
$scope module PE $end
$var wire 1 ! clk $end
$var wire 1 " reset $end
$var wire 1 # z $end
$var wire 16 $ result [15:0] $end
$var wire 16 % op2_12 [15:0] $end
$var wire 16 & ir_23 [15:0] $end
$var wire 16 ' ir_12 [15:0] $end
$var wire 16 ( ir_01 [15:0] $end
$var wire 1 ) haltedP $end
$var wire 16 * Rd_12 [15:0] $end
$var wire 16 + PCs4_to_reg [15:0] $end
$var wire 16 , PCfollow_23 [15:0] $end
$var wire 16 - PCfollow_12 [15:0] $end
$var wire 16 . PCfollow_01 [15:0] $end
$var reg 1 / halt $end
$scope module s0 $end
$var wire 16 0 R15 [15:0] $end
$var wire 1 ! clk $end
$var wire 1 1 insertNOP $end
$var wire 16 2 irInitial [15:0] $end
$var wire 1 " reset $end
$var wire 16 3 ir [15:0] $end
$var wire 1 ) halt $end
$var wire 1 # Z $end
$var wire 2 4 CC [1:0] $end
$var reg 16 5 PC [15:0] $end
$var reg 16 6 PCfollow [15:0] $end
$upscope $end
$scope module s1 $end
$var wire 16 7 Rd_out [15:0] $end
$var wire 1 ! clk $end
$var wire 16 8 ir [15:0] $end
$var wire 16 9 pc [15:0] $end
$var wire 1 " reset $end
$var wire 16 : pc_to_reg [15:0] $end
$var wire 5 ; op_code [4:0] $end
$var wire 16 < op2_out [15:0] $end
$var wire 1 = immFlag $end
$var wire 2 > cc [1:0] $end
$var wire 1 ? Rd $end
$var reg 16 @ ir_out [15:0] $end
$var reg 16 A pc_follow [15:0] $end
$var reg 12 B pre [11:0] $end
$var reg 1 C preFlag $end
$upscope $end
$scope module s2 $end
$var wire 16 D addr [15:0] $end
$var wire 1 ! clk $end
$var wire 16 E data [15:0] $end
$var wire 16 F ir_in [15:0] $end
$var wire 16 G pc [15:0] $end
$var wire 1 " reset $end
$var wire 5 H op [4:0] $end
$var reg 16 I addr_latch [15:0] $end
$var reg 16 J data_latch [15:0] $end
$var reg 16 K ir_out [15:0] $end
$var reg 16 L pc_follow [15:0] $end
$var reg 16 M value_out [15:0] $end
$upscope $end
$scope module s3 $end
$var wire 1 ! clk $end
$var wire 16 N ir_in [15:0] $end
$var wire 16 O pc [15:0] $end
$var wire 1 " reset $end
$var wire 16 P result [15:0] $end
$var wire 1 Q Rd $end
$var reg 2 R cc [1:0] $end
$var reg 5 S opcode [4:0] $end
$var reg 16 T pc_follow [15:0] $end
$var reg 1 # z_reg $end
$upscope $end
$upscope $end
$upscope $end
$enddefinitions $end
#0
$dumpvars
bx T
bx S
bx R
xQ
bx P
bx O
bx N
bx M
bx L
bx K
bx J
bx I
bx H
bx G
bx F
b100 E
b0 D
0C
b0 B
bx A
bx @
0?
b0 >
1=
b100 <
b0 ;
bx :
bx 9
b100000100 8
b0 7
bx 6
b0 5
b0 4
b100000100 3
b100000100 2
01
b0 0
0/
bx .
bx -
bx ,
bx +
b0 *
0)
b100000100 (
bx '
bx &
b100 %
bx $
0#
0"
0!
$end
#10
1"
#20
0"
#30
b0 %
b0 <
b0 E
b10100 ;
0=
b1010000000000000 (
b1010000000000000 3
b1010000000000000 8
b0 H
b1010000000000000 2
b1 5
b0 .
b0 6
b0 9
b100000100 '
b100000100 @
b100000100 F
b0 I
b100 J
b0 $
b0 M
b0 P
1!
#40
0!
#50
0Q
b10100 H
b100000100 &
b100000100 K
b100000100 N
b0 J
b1010000000000000 '
b1010000000000000 @
b1010000000000000 F
b0 -
b0 A
b0 G
b10 5
b1 .
b1 6
b1 9
b100 $
b100 M
b100 P
1!
#60
0!
#70
b11 5
b10 .
b10 6
b10 9
b1 -
b1 A
b1 G
b1010000000000000 &
b1010000000000000 K
b1010000000000000 N
b0 ,
b0 L
b0 O
b100 I
b100 %
b100 <
b100 E
b0 $
b0 M
b0 P
b100 *
b100 7
b100 D
b0 S
b0 R
1!
#80
0!
#90
b11 %
b11 <
b11 E
b0 ;
1=
b100000011 (
b100000011 3
b100000011 8
b1 ,
b1 L
b1 O
b100 J
b10 -
b10 A
b10 G
b100000011 2
b100 5
b11 .
b11 6
b11 9
b10100 S
1!
#100
0!
#110
b100 %
b100 <
b100 E
b10100 ;
0=
b1010000000000000 (
b1010000000000000 3
b1010000000000000 8
b0 H
b1010000000000000 2
b101 5
b100 .
b100 6
b100 9
b100000011 '
b100000011 @
b100000011 F
b11 -
b11 A
b11 G
b10 ,
b10 L
b10 O
b11 J
1!
#120
0!
#130
b10100 H
b100000011 &
b100000011 K
b100000011 N
b11 ,
b11 L
b11 O
b100 J
b1010000000000000 '
b1010000000000000 @
b1010000000000000 F
b100 -
b100 A
b100 G
b110 5
b101 .
b101 6
b101 9
b111 $
b111 M
b111 P
1!
#140
0!
#150
b111 5
b110 .
b110 6
b110 9
b101 -
b101 A
b101 G
b1010000000000000 &
b1010000000000000 K
b1010000000000000 N
b100 ,
b100 L
b100 O
b111 I
b111 %
b111 <
b111 E
b0 $
b0 M
b0 P
b111 *
b111 7
b111 D
b0 S
1!
#160
0!
#170
b10 %
b10 <
b10 E
b0 ;
1=
b100000010 (
b100000010 3
b100000010 8
b101 ,
b101 L
b101 O
b111 J
b110 -
b110 A
b110 G
b100000010 2
b1000 5
b111 .
b111 6
b111 9
b10100 S
1!
#180
0!
#190
b111 %
b111 <
b111 E
b10100 ;
0=
b1010000000000000 (
b1010000000000000 3
b1010000000000000 8
b0 H
b1010000000000000 2
b1001 5
b1000 .
b1000 6
b1000 9
b100000010 '
b100000010 @
b100000010 F
b111 -
b111 A
b111 G
b110 ,
b110 L
b110 O
b10 J
1!
#200
0!
#210
b10100 H
b100000010 &
b100000010 K
b100000010 N
b111 ,
b111 L
b111 O
b111 J
b1010000000000000 '
b1010000000000000 @
b1010000000000000 F
b1000 -
b1000 A
b1000 G
b1010 5
b1001 .
b1001 6
b1001 9
b1001 $
b1001 M
b1001 P
1!
#220
0!
#230
b1011 5
b1010 .
b1010 6
b1010 9
b1001 -
b1001 A
b1001 G
b1010000000000000 &
b1010000000000000 K
b1010000000000000 N
b1000 ,
b1000 L
b1000 O
b1001 I
b1001 %
b1001 <
b1001 E
b0 $
b0 M
b0 P
b1001 *
b1001 7
b1001 D
b0 S
1!
#240
0!
#250
1)
b10011 ;
b1001100000000000 (
b1001100000000000 3
b1001100000000000 8
b1001 ,
b1001 L
b1001 O
b1001 J
b1010 -
b1010 A
b1010 G
b1001100000000000 2
b1100 5
b1011 .
b1011 6
b1011 9
b10100 S
1!
#260
0!
#270
bx %
bx <
bx E
x1
bx *
bx 7
bx D
x?
x)
bx ;
bx >
x=
bx 4
bx (
bx 3
bx 8
b10011 H
bx 2
b1101 5
b1100 .
b1100 6
b1100 9
b1001100000000000 '
b1001100000000000 @
b1001100000000000 F
b1011 -
b1011 A
b1011 G
b1010 ,
b1010 L
b1010 O
1/
1!
