pinkyCGI.v
//
`define INST_END_INDEX	20

//common bit lengths
`define WORD 		[15:0]
`define OPCODE 		[15:11]
`define CC			[10:9]
`define IMM			[8]
`define DEST		[7:4]
`define	OP2			[3:0]
`define REGS		[15:0]
`define PC			registers[15]
`define SIZE		[65535:0]
`define PRESIZE		[11:0]
`define BASEOPS		[3:0]

//stage 
`define	STAGE       [1:0]		
`define STAGE0		0
`define STAGE1		1
`define	STAGE2		2
`define STAGE3		3

//OPCODES
`define OPADD 	5'b00000
`define OPADDF 	5'b00001
`define OPAND	5'b00010
`define OPBIC	5'b00011
`define OPEOR	5'b00100
`define OPFTOI  5'b00101
`define OPITOF  5'b00110
`define OPLDR   5'b00111
`define OPMOV   5'b01000
`define OPMUL   5'b01001
`define OPMULF  5'b01010
`define OPNEG   5'b01011
`define OPORR   5'b01100
`define OPRECF  5'b01101
`define OPSHA   5'b01110
`define OPSTR   5'b01111
`define OPSLT   5'b10000
`define OPSUB   5'b10001
`define OPSUBF  5'b10010
`define OPSYS   5'b10011
`define OPNOP   5'b10100
//5'b10101
//5'b10110
//5'b10111
`define OPPRE   5'b11000


//CC values
`define	AL			0
`define S 			1
`define EQ			2
`define NE			3	

//OP2 MACRO
`define Op2struct(IR, PRE, PREFLAG, REGFILE) \
	(IR `IMM ? { PREFLAG ? {IR `OP2, PRE} : {12{IR[3]}}, IR `OP2 } : REGFILE[IR `OP2] )

module stage0(PCfollow,ir,halt, R15,Z,clk,reset);
			  
output reg `WORD PCfollow;
output `WORD ir;
output halt;
input `WORD R15;
input Z,clk,reset;

reg [2:0] in_pipe `REGS;

reg `WORD instmem `SIZE;	
reg `WORD PC;				
wire `WORD irInitial;
wire checkCodes;
wire [1:0] CC;
reg [1:0] counter;
reg a;

initial begin
    a = 0;
    repeat(16)begin
	in_pipe [a] = 2'b0;	
	a = a + 1;
    end
end

always@(reset) begin
	PC = 0;
	$readmemh("inst.txt", instmem, 0, `INST_END_INDEX);
end

always@(posedge clk) begin
	PCfollow <= PC;
	PC <= PC + 1;
    end
//always@(posedge clk) begin
//    if(counter == 0)begin
//	PCfollow <= PC;
//	PC <= PC + 1;
//	counter <= 2;
//    end else begin
//	counter <= counter - 1;
//    end
//end

assign irInitial = instmem[PC];
assign CC = irInitial `CC;
assign insertNOP = ((CC == `NE)&&(Z == 1))||((CC == `EQ)&&(Z == 0));
assign ir = (insertNOP == 1)? {`OPNOP,11'h000} : instmem[PC];
assign halt = (ir `OPCODE == `OPSYS);

endmodule


module stage1(pc_follow, pc_to_reg, ir_out, Rd_out, op2_out, halt_out, halt_in, ir, clk, reset, pc);
output reg `WORD pc_follow;
output `WORD Rd_out, op2_out;
output reg `WORD ir_out;
output reg halt_out;
input halt_in;
input `WORD ir, pc_to_reg;
input clk, reset;
input `WORD pc;

wire [4:0] op_code;
wire [3:0] Rd;
wire [1:0] cc;
wire immFlag;

reg preFlag;
reg `PRESIZE pre, pre_temp;



always@(reset)begin
    preFlag = 0;
    pre = 0;
    halt_out = 0;
end

//split up instruction word into the separate chunks
assign op_code = ir `OPCODE;
assign cc = ir `CC;
assign immFlag = ir `IMM;
assign Rd = ir `DEST;
assign Rd_out = PE.regfile[Rd];

//`define Op2struct(IR, PRE, PREFLAG, REGFILE) \
//	(IR `IMM ? { PREFLAG ? {PRE, IR `OP2} : {12{IR[3]}}, IR `OP2 } : REGFILE[IR `OP2] )
assign op2_out = (ir[15] & ir[14]) ? 16'h0000 :  `Op2struct(ir, pre, preFlag, PE.regfile);

//assign pre = pre_temp;
//assign pre = (ir[15] & ir[14]) ? ir `PRESIZE : pre_temp;
//assign preFlag = ir[15] & ir[14];
//assign Rn = ir `OP2;

always@(posedge clk)begin
    if(ir[15] & ir[14]) 
	begin
	preFlag = 1;
	pre = ir `PRESIZE;
	end
    else if(immFlag) preFlag = 0;
    
    pc_follow <= pc;
    ir_out <= ir;
    halt_out <= halt_in;
    //Rd_out <= regfile[Rd];
    //op2_out <= (ir[15] & ir[14]) ? 16'h0000 :  `Op2struct(ir, pre, preFlag, regfile);
end
endmodule

module stage2(pc_follow, ir_out, value_out, halt_out, halt_in, ir_in, addr, data, clk, reset, pc);
output reg `WORD pc_follow;
output reg `WORD value_out;
output reg `WORD ir_out;
output reg halt_out;
input halt_in;
input `WORD addr, data, pc;
input clk, reset;
input `WORD ir_in;
reg `WORD datamem `SIZE;
reg `WORD addr_latch, data_latch;

wire [4:0]op;
assign op = ir_in `OPCODE;

//do the ALU thing
//when comparing to the PinKY instruction set
//Rd is addr and Op2 is data

always@(reset)begin
    //only reading in 16 data mem locations for now
    $readmemh("data.txt", datamem, 0, 15);
    halt_out = 0;
end


always@(posedge clk)begin
    case(op)
        `OPADD : begin  value_out = addr_latch + data_latch;end
        `OPAND : begin  value_out = addr_latch & data_latch;end
        `OPBIC : begin  value_out = addr_latch & ~data_latch;end
        `OPEOR : begin  value_out = addr_latch ^ data_latch;end
        `OPLDR : begin  value_out = datamem[data_latch];end
        `OPMOV : begin  value_out = data_latch;end
        `OPMUL : begin  value_out = addr_latch * data_latch;end
        `OPNEG : begin  value_out = -data_latch;end
        `OPORR : begin  value_out = addr_latch | data_latch;end
        `OPSHA : begin  value_out = (data_latch>0) ? addr_latch<<data_latch : addr_latch>>-data_latch;end
        `OPSTR : begin datamem[addr_latch] = data_latch; value_out = data_latch;end
        `OPSLT : begin  value_out = (addr_latch<data_latch);end
        `OPSUB : begin  value_out = addr_latch - data_latch;end
    //we'll catch these in the default case
    //    `OPSYS : begin ; end
    //    `OPNOP : begin ; end
    //    `OPPRE : begin ; end
        default : begin value_out = 16'h0000; end
    endcase
    data_latch <= data;
    addr_latch <= addr;
    pc_follow <= pc;
    ir_out <= ir_in;
    halt_out <= halt_in;
end
endmodule

module stage3(pc_follow, z_reg, halt_out, halt_in, ir_in, result, clk, reset, pc);
input `WORD result, pc;
input `WORD ir_in;
input clk, reset;
output reg halt_out;
input halt_in;
output reg `WORD pc_follow;
output reg z_reg; //should this be a reg?

reg [4:0] opcode;
wire [1:0] cc;
wire z;
wire [3:0] Rd;
reg dummy;

assign Rd = ir_in `DEST;

//assign z = (cc == `S) ? z : (((result == 16'h0000) & (cc == `S)) ? 1'b1 : 1'b0);

always@(reset)begin
    z_reg = 0;
    halt_out = 0;
end

assign cc = ir_in `CC;

always@(posedge clk)begin
    opcode = ir_in `OPCODE;

    if (cc == `S)begin
	if (result == 16'h0000) z_reg = 1'b1;
	else z_reg = 1'b0;
    end
    
    case(opcode)
	//`OPSYS : begin dummy = 1; end
	//`OPPRE : begin dummy = 1; end
	`OPSYS : ;
	`OPPRE : ;
	`OPNOP : ;
	default: begin PE.regfile[Rd] = result; end
    endcase	

    halt_out <= halt_in;	
end
endmodule


module processor(halt, reset, clk);
output reg halt;
input reset, clk;

//the underscore<digit><digit> notation indicates control flow
//for example _12 means it goes from stage 1 to stage 2
wire `WORD PCfollow_01, PCfollow_12, PCfollow_23, PCs4_to_reg;
wire `WORD ir_01, ir_12, ir_23;
wire halt_01, halt_12, halt_23, halt_final;
wire `WORD Rd_12, op2_12;
wire `WORD result;
wire z;
reg `WORD regfile `REGS;

always @(reset)begin
    $readmemh("regs.txt", regfile, 0, 15);
end

always @(posedge clk) begin
halt <= halt_final;
end

//module stage0(PCfollow,ir,halt, R15,Z,clk,reset);
stage0 s0(PCfollow_01,ir_01,halt_01,16'h0000,z,clk,reset);

//module stage1(pc_follow, pc_to_reg, ir_out, Rd_out, op2_out, halt_out, halt_in, ir, clk, reset, pc);
stage1 s1(PCfollow_12, PCs4_to_reg, ir_12, Rd_12, op2_12, halt_12, halt_01, ir_01, clk, reset, PCfollow_01);

//module stage2(pc_follow, ir_out, value_out, halt_out, halt_in, ir_in, addr, data, clk, reset, pc);
stage2 s2(PCfollow_23, ir_23, result, halt_23, halt_12, ir_12, Rd_12, op2_12, clk, reset, PCfollow_12);

//module stage3(pc_follow, z_reg, halt_out, halt_in, ir_in, result, clk, reset, pc);
stage3 s3(PCs4_to_reg, z, halt_final, halt_23, ir_23, result, clk, reset, PCfollow_23);

always @(reset) begin
	halt = 0;
end

endmodule

module testbench;
reg reset = 0;
reg clk = 0;
wire halted;
processor PE(halted, reset, clk);
initial begin
  $dumpfile("dumpfile.vcd");
  $dumpvars(0,PE);
  #10 reset = 1;
  #10 reset = 0;
  while (!halted) begin
    #10 clk = 1;
    #10 clk = 0;
  end
  $finish;
end
endmodule

dumpfile.vcd
$date
	Thu Nov  1 17:35:41 2018
$end
$version
	Icarus Verilog
$end
$timescale
	1s
$end
$scope module testbench $end
$scope module PE $end
$var wire 1 ! clk $end
$var wire 1 " reset $end
$var wire 1 # z $end
$var wire 16 $ result [15:0] $end
$var wire 16 % op2_12 [15:0] $end
$var wire 16 & ir_23 [15:0] $end
$var wire 16 ' ir_12 [15:0] $end
$var wire 16 ( ir_01 [15:0] $end
$var wire 1 ) halt_final $end
$var wire 1 * halt_23 $end
$var wire 1 + halt_12 $end
$var wire 1 , halt_01 $end
$var wire 16 - Rd_12 [15:0] $end
$var wire 16 . PCs4_to_reg [15:0] $end
$var wire 16 / PCfollow_23 [15:0] $end
$var wire 16 0 PCfollow_12 [15:0] $end
$var wire 16 1 PCfollow_01 [15:0] $end
$var reg 1 2 halt $end
$scope module s0 $end
$var wire 16 3 R15 [15:0] $end
$var wire 1 ! clk $end
$var wire 1 4 insertNOP $end
$var wire 16 5 irInitial [15:0] $end
$var wire 1 " reset $end
$var wire 16 6 ir [15:0] $end
$var wire 1 , halt $end
$var wire 1 # Z $end
$var wire 2 7 CC [1:0] $end
$var reg 16 8 PC [15:0] $end
$var reg 16 9 PCfollow [15:0] $end
$var reg 1 : a $end
$upscope $end
$scope module s1 $end
$var wire 16 ; Rd_out [15:0] $end
$var wire 1 ! clk $end
$var wire 1 , halt_in $end
$var wire 16 < ir [15:0] $end
$var wire 16 = pc [15:0] $end
$var wire 1 " reset $end
$var wire 16 > pc_to_reg [15:0] $end
$var wire 5 ? op_code [4:0] $end
$var wire 16 @ op2_out [15:0] $end
$var wire 1 A immFlag $end
$var wire 2 B cc [1:0] $end
$var wire 4 C Rd [3:0] $end
$var reg 1 + halt_out $end
$var reg 16 D ir_out [15:0] $end
$var reg 16 E pc_follow [15:0] $end
$var reg 12 F pre [11:0] $end
$var reg 1 G preFlag $end
$upscope $end
$scope module s2 $end
$var wire 16 H addr [15:0] $end
$var wire 1 ! clk $end
$var wire 16 I data [15:0] $end
$var wire 1 + halt_in $end
$var wire 16 J ir_in [15:0] $end
$var wire 16 K pc [15:0] $end
$var wire 1 " reset $end
$var wire 5 L op [4:0] $end
$var reg 16 M addr_latch [15:0] $end
$var reg 16 N data_latch [15:0] $end
$var reg 1 * halt_out $end
$var reg 16 O ir_out [15:0] $end
$var reg 16 P pc_follow [15:0] $end
$var reg 16 Q value_out [15:0] $end
$upscope $end
$scope module s3 $end
$var wire 1 ! clk $end
$var wire 1 * halt_in $end
$var wire 16 R ir_in [15:0] $end
$var wire 16 S pc [15:0] $end
$var wire 1 " reset $end
$var wire 16 T result [15:0] $end
$var wire 2 U cc [1:0] $end
$var wire 4 V Rd [3:0] $end
$var reg 1 ) halt_out $end
$var reg 5 W opcode [4:0] $end
$var reg 16 X pc_follow [15:0] $end
$var reg 1 # z_reg $end
$upscope $end
$upscope $end
$upscope $end
$enddefinitions $end
#0
$dumpvars
bx X
bx W
bx V
bx U
bx T
bx S
bx R
bx Q
bx P
bx O
bx N
bx M
bx L
bx K
bx J
b0 I
b0 H
0G
b0 F
bx E
bx D
b0 C
b1 B
1A
b0 @
b0 ?
bx >
bx =
b1100000000 <
b0 ;
0:
bx 9
b0 8
b1 7
b1100000000 6
b1100000000 5
04
b0 3
02
bx 1
bx 0
bx /
bx .
b0 -
0,
0+
0*
0)
b1100000000 (
bx '
bx &
b0 %
bx $
0#
0"
0!
$end
#10
1"
#20
0"
#30
b10100 ?
b0 B
0A
b0 7
b1010000000000000 (
b1010000000000000 6
b1010000000000000 <
b0 L
b1010000000000000 5
b1 8
b0 1
b0 9
b0 =
b1100000000 '
b1100000000 D
b1100000000 J
b0 M
b0 N
b0 $
b0 Q
b0 T
1!
#40
0!
#50
b0 V
b1 U
b10100 L
b1100000000 &
b1100000000 O
b1100000000 R
b1010000000000000 '
b1010000000000000 D
b1010000000000000 J
b0 0
b0 E
b0 K
b10 8
b1 1
b1 9
b1 =
1!
#60
0!
#70
b0 U
b11 8
b10 1
b10 9
b10 =
b1 0
b1 E
b1 K
b1010000000000000 &
b1010000000000000 O
b1010000000000000 R
b0 /
b0 P
b0 S
1#
b0 W
1!
#80
0!
#90
b0 %
b0 @
b0 I
14
b10100 ?
b0 B
0A
b0 C
b11 7
b1010000000000000 (
b1010000000000000 6
b1010000000000000 <
b1 /
b1 P
b1 S
b10 0
b10 E
b10 K
b11100010010 5
b100 8
b11 1
b11 9
b11 =
b10100 W
1!
#100
0!
#110
04
b0 7
b1010000000000000 5
b101 8
b100 1
b100 9
b100 =
b11 0
b11 E
b11 K
b10 /
b10 P
b10 S
1!
#120
0!
#130
b11 /
b11 P
b11 S
b100 0
b100 E
b100 K
b110 8
b101 1
b101 9
b101 =
1!
#140
0!
#150
b111 8
b110 1
b110 9
b110 =
b101 0
b101 E
b101 K
b100 /
b100 P
b100 S
1!
#160
0!
#170
1,
b10011 ?
b1001100000000000 (
b1001100000000000 6
b1001100000000000 <
b101 /
b101 P
b101 S
b110 0
b110 E
b110 K
b1001100000000000 5
b1000 8
b111 1
b111 9
b111 =
1!
#180
0!
#190
0,
b10100 ?
b1010000000000000 (
b1010000000000000 6
b1010000000000000 <
b10011 L
b1010000000000000 5
b1001 8
b1000 1
b1000 9
b1000 =
1+
b1001100000000000 '
b1001100000000000 D
b1001100000000000 J
b111 0
b111 E
b111 K
b110 /
b110 P
b110 S
1!
#200
0!
#210
b10100 L
1*
b1001100000000000 &
b1001100000000000 O
b1001100000000000 R
b111 /
b111 P
b111 S
0+
b1010000000000000 '
b1010000000000000 D
b1010000000000000 J
b1000 0
b1000 E
b1000 K
b1010 8
b1001 1
b1001 9
b1001 =
1!
#220
0!
#230
b1011 8
b1010 1
b1010 9
b1010 =
b1001 0
b1001 E
b1001 K
0*
b1010000000000000 &
b1010000000000000 O
b1010000000000000 R
b1000 /
b1000 P
b1000 S
1)
b10011 W
1!
#240
0!
#250
bx %
bx @
bx I
x4
x,
bx ?
bx B
xA
bx -
bx ;
bx H
bx C
bx 7
bx (
bx 6
bx <
12
0)
b1001 /
b1001 P
b1001 S
b1010 0
b1010 E
b1010 K
bx 5
b1100 8
b1011 1
b1011 9
b1011 =
b10100 W
1!
