pinkyCGI.v
//
`define INST_END_INDEX	6

//common bit lengths
`define WORD 		[15:0]
`define OPCODE 		[15:11]
`define CC			[10:9]
`define IMM			[8]
`define DEST		[7:4]
`define	OP2			[3:0]
`define REGS		[15:0]
`define PC			registers[15]
`define SIZE		[65535:0]
`define PRESIZE		[11:0]
`define BASEOPS		[3:0]

//stage 
`define	STAGE       [1:0]		
`define STAGE0		0
`define STAGE1		1
`define	STAGE2		2
`define STAGE3		3

//OPCODES
`define OPADD 	5'b00000
`define OPADDF 	5'b00001
`define OPAND	5'b00010
`define OPBIC	5'b00011
`define OPEOR	5'b00100
`define OPFTOI  5'b00101
`define OPITOF  5'b00110
`define OPLDR   5'b00111
`define OPMOV   5'b01000
`define OPMUL   5'b01001
`define OPMULF  5'b01010
`define OPNEG   5'b01011
`define OPORR   5'b01100
`define OPRECF  5'b01101
`define OPSHA   5'b01110
`define OPSTR   5'b01111
`define OPSLT   5'b10000
`define OPSUB   5'b10001
`define OPSUBF  5'b10010
`define OPSYS   5'b10011
`define OPNOP   5'b10100
//5'b10101
//5'b10110
//5'b10111
`define OPPRE   5'b11000


//CC values
`define	AL			0
`define S 			1
`define NE			2
`define EQ			3

//OP2 MACRO
`define Op2struct(IR, PRE, PREFLAG, REGFILE) \
	(IR `IMM ? { PREFLAG ? {IR `OP2, PRE} : {12{IR[3]}}, IR `OP2 } : REGFILE[IR `OP2] )

module stage0(PCfollow,ir,halt,R15,Z,clk,reset);
			  
output reg `WORD PCfollow;
output `WORD ir;
output halt;
input `WORD R15;
input Z,clk,reset;

reg `WORD instmem `SIZE;	
reg `WORD PC;				
wire `WORD irInitial;
wire checkCodes;
wire [1:0] CC;

always@(reset) begin
	PC = 0;
	$readmemh("inst.txt", instmem, 0, `INST_END_INDEX);
end

always@(posedge clk) begin
	PCfollow <= PC;
	PC <= PC + 1;
end

assign irInitial = instmem[PC];
assign CC = irInitial `CC;
assign insertNOP = ((CC == `NE)&&(Z == 1))||((CC == `EQ)&&(Z == 0));
assign ir = (insertNOP == 1)? {`OPNOP,11'h000} : instmem[PC];
assign halt = (ir `OPCODE == `OPSYS);

endmodule


module stage1(pc_follow, pc_to_reg, op_cc_out, Rd_out, op2_out, ir, clk, reset, pc);
output reg `WORD pc_follow;
output `WORD Rd_out, op2_out;
output reg [6:0] op_cc_out;
input `WORD ir, pc_to_reg;
input clk, reset;
input `WORD pc;

wire [4:0] op_code;
wire [1:0] cc;
wire immFlag;

reg `WORD regfile `REGS;
reg preFlag;
reg `PRESIZE pre, pre_temp;



always@(reset)begin
    $readmemh("regs.txt", regfile, 0, 15);
    preFlag = 0;
    pre = 0;

end

//split up instruction word into the separate chunks
assign op_code = ir `OPCODE;
assign cc = ir `CC;
assign immFlag = ir `IMM;
assign Rd = ir `DEST;
assign Rd_out = regfile[Rd];

//`define Op2struct(IR, PRE, PREFLAG, REGFILE) \
//	(IR `IMM ? { PREFLAG ? {PRE, IR `OP2} : {12{IR[3]}}, IR `OP2 } : REGFILE[IR `OP2] )
assign op2_out = (ir[15] & ir[14]) ? 16'h0000 :  `Op2struct(ir, pre, preFlag, regfile);

//assign pre = pre_temp;
//assign pre = (ir[15] & ir[14]) ? ir `PRESIZE : pre_temp;
//assign preFlag = ir[15] & ir[14];
//assign Rn = ir `OP2;

always@(posedge clk)begin
    if(ir[15] & ir[14]) 
	begin
	preFlag = 1;
	pre = ir `PRESIZE;
	end
    else if(immFlag) preFlag = 0;
    
    pc_follow <= pc;
    op_cc_out <= {op_code, cc};
    //Rd_out <= regfile[Rd];
    //op2_out <= (ir[15] & ir[14]) ? 16'h0000 :  `Op2struct(ir, pre, preFlag, regfile);
end
endmodule

module stage2(pc_follow, op_cc_out, value_out, op_cc_in, addr, data, clk, reset, pc);
output reg `WORD pc_follow;
output reg `WORD value_out;
output reg [6:0]  op_cc_out;
input `WORD addr, data, pc;
input clk, reset;
input [6:0] op_cc_in;
reg `WORD datamem `SIZE;
reg `WORD data_latch;

wire [4:0]op;
assign op = op_cc_in[6:2];

//do the ALU thing
//when comparing to the PinKY instruction set
//Rd is addr and Op2 is data

always@(reset)begin
    //only reading in 16 data mem locations for now
    $readmemh("data.txt", datamem, 0, 15);
end


always@(posedge clk)begin
    case(op)
        `OPADD : begin  value_out = addr + data_latch; end
        `OPAND : begin  value_out = addr & data_latch; end
        `OPBIC : begin  value_out = addr & ~data_latch; end
        `OPEOR : begin  value_out = addr ^ data_latch; end
        `OPLDR : begin  value_out = datamem[data_latch]; end
        `OPMOV : begin  value_out = data_latch; end
        `OPMUL : begin  value_out = addr * data_latch; end
        `OPNEG : begin  value_out = -data_latch; end
        `OPORR : begin  value_out = addr | data_latch; end
        `OPSHA : begin  value_out = (data_latch>0) ? addr<<data_latch : addr>>-data_latch; end
        `OPSTR : begin datamem[addr] = data_latch; value_out = data_latch; end
        `OPSLT : begin  value_out = (addr<data_latch); end
        `OPSUB : begin  value_out = addr - data_latch; end
    //we'll catch these in the default case
    //    `OPSYS : begin ; end
    //    `OPNOP : begin ; end
    //    `OPPRE : begin ; end
        default : begin value_out = 16'h0000; end
    endcase
    data_latch <= data;
    pc_follow <= pc;
    op_cc_out <= op_cc_in;
end

endmodule

module stage3(pc_follow, z_out, op_cc_in, result, clk, reset, pc);
input `WORD result, pc;
input [6:0] op_cc_in;
input clk, reset;
output reg `WORD pc_follow;
output reg z_out; //should this be a reg?

wire [1:0] cc;
wire z;

assign cc = op_cc_in[1:0];

//if(cc[0] & !cc[1])begin
//    //we need to set Z reg appropriately
//    case(result)
//	16'h0000: assign z = 1'b1;
//	default: assign z = 1'b0;
//    endcase
//end

always@(posedge clk)begin
    z_out <= z; 
end
endmodule


module processor(halt, reset, clk);
output reg halt;
input reset, clk;

//the underscore<digit><digit> notation indicates control flow
//for example _12 means it goes from stage 1 to stage 2
wire `WORD PCfollow_01, PCfollow_12, PCfollow_23, PCs4_to_reg;
wire `WORD ir;
wire haltedP;
wire `WORD Rd_12, op2_12;
wire [6:0] op_cc_12, op_cc_23;
wire `WORD result;
wire z;

always @(posedge clk) begin
halt <= haltedP;
end

//module stage0(PCfollow,ir,halt,R15,Z,clk,reset);
stage0 s0(PCfollow_01,ir,haltedP,16'h0000,1'b0,clk,reset);

//module stage1(pc_follow, op_cc_out, Rd_out, op2_out, ir, clk, reset, pc);
stage1 s1(PCfollow_12, PCs4_to_reg, op_cc_12, Rd_12, op2_12, ir, clk, reset, PCfollow_01);

//module stage2(pc_follow, op_cc_out, value_out, op_cc_in, addr, data, clk, reset, pc);
stage2 s2(PCfollow_23, op_cc_23, result, op_cc_12, Rd_12, op2_12, clk, reset, PCfollow_12);

//module stage3(pc_follow, z_out, op_cc_in, result, clk, reset, pc);
stage3 s3(PCs4_to_reg, z, op_cc_23, result, clk, reset, PCfollow_23);

always @(reset) begin
	halt = 0;
end

endmodule

module testbench;
reg reset = 0;
reg clk = 0;
wire halted;
processor PE(halted, reset, clk);
initial begin
  $dumpfile("dumpfile.vcd");
  $dumpvars(0,PE);
  #10 reset = 1;
  #10 reset = 0;
  while (!halted) begin
    #10 clk = 1;
    #10 clk = 0;
  end
  $finish;
end
endmodule

dumpfile.vcd
$date
	Wed Oct 31 17:03:34 2018
$end
$version
	Icarus Verilog
$end
$timescale
	1s
$end
$scope module testbench $end
$scope module PE $end
$var wire 1 ! clk $end
$var wire 1 " reset $end
$var wire 1 # z $end
$var wire 16 $ result [15:0] $end
$var wire 7 % op_cc_23 [6:0] $end
$var wire 7 & op_cc_12 [6:0] $end
$var wire 16 ' op2_12 [15:0] $end
$var wire 16 ( ir [15:0] $end
$var wire 1 ) haltedP $end
$var wire 16 * Rd_12 [15:0] $end
$var wire 16 + PCs4_to_reg [15:0] $end
$var wire 16 , PCfollow_23 [15:0] $end
$var wire 16 - PCfollow_12 [15:0] $end
$var wire 16 . PCfollow_01 [15:0] $end
$var reg 1 / halt $end
$scope module s0 $end
$var wire 16 0 R15 [15:0] $end
$var wire 1 1 Z $end
$var wire 1 ! clk $end
$var wire 1 2 insertNOP $end
$var wire 16 3 irInitial [15:0] $end
$var wire 1 " reset $end
$var wire 16 4 ir [15:0] $end
$var wire 1 ) halt $end
$var wire 2 5 CC [1:0] $end
$var reg 16 6 PC [15:0] $end
$var reg 16 7 PCfollow [15:0] $end
$upscope $end
$scope module s1 $end
$var wire 16 8 Rd_out [15:0] $end
$var wire 1 ! clk $end
$var wire 16 9 ir [15:0] $end
$var wire 16 : pc [15:0] $end
$var wire 1 " reset $end
$var wire 16 ; pc_to_reg [15:0] $end
$var wire 5 < op_code [4:0] $end
$var wire 16 = op2_out [15:0] $end
$var wire 1 > immFlag $end
$var wire 2 ? cc [1:0] $end
$var wire 1 @ Rd $end
$var reg 7 A op_cc_out [6:0] $end
$var reg 16 B pc_follow [15:0] $end
$var reg 12 C pre [11:0] $end
$var reg 1 D preFlag $end
$upscope $end
$scope module s2 $end
$var wire 16 E addr [15:0] $end
$var wire 1 ! clk $end
$var wire 16 F data [15:0] $end
$var wire 7 G op_cc_in [6:0] $end
$var wire 16 H pc [15:0] $end
$var wire 1 " reset $end
$var wire 5 I op [4:0] $end
$var reg 16 J data_latch [15:0] $end
$var reg 7 K op_cc_out [6:0] $end
$var reg 16 L pc_follow [15:0] $end
$var reg 16 M value_out [15:0] $end
$upscope $end
$scope module s3 $end
$var wire 1 ! clk $end
$var wire 7 N op_cc_in [6:0] $end
$var wire 16 O pc [15:0] $end
$var wire 1 " reset $end
$var wire 16 P result [15:0] $end
$var wire 1 Q z $end
$var wire 2 R cc [1:0] $end
$var reg 16 S pc_follow [15:0] $end
$var reg 1 # z_out $end
$upscope $end
$upscope $end
$upscope $end
$enddefinitions $end
#0
$dumpvars
bx S
bx R
zQ
bx P
bx O
bx N
bx M
bx L
bx K
bx J
bx I
bx H
bx G
b100 F
b0 E
0D
b0 C
bx B
bx A
1@
b0 ?
1>
b100 =
b1000 <
bx ;
bx :
b100000100010100 9
b0 8
bx 7
b0 6
b0 5
b100000100010100 4
b100000100010100 3
02
01
b0 0
0/
bx .
bx -
bx ,
bx +
b0 *
0)
b100000100010100 (
b100 '
bx &
bx %
bx $
x#
0"
0!
$end
#10
1"
#20
0"
#30
b10 '
b10 =
b10 F
b10001 <
b1000100100010010 (
b1000100100010010 4
b1000100100010010 9
b1000 I
b1000100100010010 3
b1 6
b0 .
b0 7
b0 :
b100000 &
b100000 A
b100000 G
b100 J
z#
b0 $
b0 M
b0 P
1!
#40
0!
#50
b0 '
b0 =
b0 F
0@
0>
12
b10100 <
b0 ?
b0 R
b10001 I
b11 5
b1010000000000000 (
b1010000000000000 4
b1010000000000000 9
b100000 %
b100000 K
b100000 N
b10 J
b1000100 &
b1000100 A
b1000100 G
b0 -
b0 B
b0 H
b11100010010 3
b10 6
b1 .
b1 7
b1 :
b100 $
b100 M
b100 P
1!
#60
0!
#70
02
b0 5
b10100 I
b1010000000000000 3
b11 6
b10 .
b10 7
b10 :
b1010000 &
b1010000 A
b1010000 G
b1 -
b1 B
b1 H
b1000100 %
b1000100 K
b1000100 N
b0 ,
b0 L
b0 O
b0 J
b1111111111111110 $
b1111111111111110 M
b1111111111111110 P
1!
#80
0!
#90
b1010000 %
b1010000 K
b1010000 N
b1 ,
b1 L
b1 O
b10 -
b10 B
b10 H
b100 6
b11 .
b11 7
b11 :
b0 $
b0 M
b0 P
1!
#100
0!
#110
b101 6
b100 .
b100 7
b100 :
b11 -
b11 B
b11 H
b10 ,
b10 L
b10 O
1!
#120
0!
#130
1)
b10011 <
b1001100000000000 (
b1001100000000000 4
b1001100000000000 9
b11 ,
b11 L
b11 O
b100 -
b100 B
b100 H
b1001100000000000 3
b110 6
b101 .
b101 7
b101 :
1!
#140
0!
#150
bx '
bx =
bx F
x2
bx *
bx 8
bx E
x@
x)
bx <
bx ?
x>
bx 5
bx (
bx 4
bx 9
b10011 I
bx 3
b111 6
b110 .
b110 7
b110 :
b1001100 &
b1001100 A
b1001100 G
b101 -
b101 B
b101 H
b100 ,
b100 L
b100 O
1/
1!
