pinkyCGI.v
//
`define INST_END_INDEX	5

//common bit lengths
`define WORD 		[15:0]
`define OPCODE 		[15:11]
`define CC			[10:9]
`define IMM			[8]
`define DEST		[7:4]
`define	OP2			[3:0]
`define REGS		[15:0]
`define PC			registers[15]
`define SIZE		[65535:0]
`define PRESIZE		[11:0]
`define BASEOPS		[3:0]

//stage 
`define	STAGE       [1:0]		
`define STAGE0		0
`define STAGE1		1
`define	STAGE2		2
`define STAGE3		3

//OPCODES
`define OPADD 	5'b00000
`define OPADDF 	5'b00001
`define OPAND	5'b00010
`define OPBIC	5'b00011
`define OPEOR	5'b00100
`define OPFTOI  5'b00101
`define OPITOF  5'b00110
`define OPLDR   5'b00111
`define OPMOV   5'b01000
`define OPMUL   5'b01001
`define OPMULF  5'b01010
`define OPNEG   5'b01011
`define OPORR   5'b01100
`define OPRECF  5'b01101
`define OPSHA   5'b01110
`define OPSTR   5'b01111
`define OPSLT   5'b10000
`define OPSUB   5'b10001
`define OPSUBF  5'b10010
`define OPSYS   5'b10011
`define OPNOP   5'b10100
//5'b10101
//5'b10110
//5'b10111
`define OPPRE   5'b11000


//CC values
`define	AL			0
`define S 			1
`define NE			2
`define EQ			3

//OP2 MACRO
`define Op2struct(IR, PRE, PREFLAG, REGFILE) \
	(IR `IMM ? { PREFLAG ? {IR `OP2, PRE} : {12{IR[3]}}, IR `OP2 } : REGFILE[IR `OP2] )

module stage0(PCfollow,ir,halt,R15,Z,clk,reset);
			  
output reg `WORD PCfollow;
output `WORD ir;
output halt;
input `WORD R15;
input Z,clk,reset;

reg `WORD instmem `SIZE;	
reg `WORD PC;				
wire `WORD ir;	
wire `WORD irInitial;
wire checkCodes;
wire [1:0] CC;

always@(reset) begin
	PC = 0;
	$readmemh("inst.txt", instmem, 0, `INST_END_INDEX);
end

always@(posedge clk) begin
	PCfollow <= PC;
	PC <= PC + 1;
end

assign irInitial = instmem[PC];
assign CC = irInitial `CC;
assign insertNOP = ((CC == `NE)&&(Z == 1))||((CC == `EQ)&&(Z == 0));
assign ir = (insertNOP == 1)? {`OPNOP,11'h000} : instmem[PC];
assign halt = (ir `OPCODE == `OPSYS);

endmodule


module stage1(pc_follow, op_cc_out, Rd_out, op2_out, ir, clk, reset, pc);
output reg `WORD pc_follow;
output `WORD Rd_out, op2_out;
output reg [6:0] op_cc_out;
input `WORD ir;
input clk, reset;
input `WORD pc;

wire [4:0] op_code;
wire [1:0] cc;
wire immFlag;

reg `WORD regfile `REGS;
reg preFlag;
reg `PRESIZE pre, pre_temp;



always@(reset)begin
    $readmemh("regs.txt", regfile, 0, 15);
    preFlag = 0;
    pre = 0;

end

//split up instruction word into the separate chunks
assign op_code = ir `OPCODE;
assign cc = ir `CC;
assign immFlag = ir `IMM;
assign Rd = ir `DEST;
assign Rd_out = regfile[Rd];

//`define Op2struct(IR, PRE, PREFLAG, REGFILE) \
//	(IR `IMM ? { PREFLAG ? {PRE, IR `OP2} : {12{IR[3]}}, IR `OP2 } : REGFILE[IR `OP2] )
assign op2_out = (ir[15] & ir[14]) ? 16'h0000 :  `Op2struct(ir, pre, preFlag, regfile);

//assign pre = pre_temp;
//assign pre = (ir[15] & ir[14]) ? ir `PRESIZE : pre_temp;
//assign preFlag = ir[15] & ir[14];
//assign Rn = ir `OP2;

always@(posedge clk)begin
    if(ir[15] & ir[14]) 
	begin
	preFlag = 1;
	pre = ir `PRESIZE;
	end
    else if(immFlag) preFlag = 0;
    
    pc_follow <= pc;
    op_cc_out <= {op_code, cc};
    //Rd_out <= regfile[Rd];
    //op2_out <= (ir[15] & ir[14]) ? 16'h0000 :  `Op2struct(ir, pre, preFlag, regfile);
end



endmodule


module processor(halt, reset, clk);
output reg halt;
input reset, clk;

//the underscore<digit><digit> notation indicates control flow
//for example _12 means it goes from stage 1 to stage 2
wire `WORD PCfollow_01, PCfollow_12, PCfollow_23, PCfollow_30;
wire `WORD ir;
wire haltedP;
wire `WORD Rd_12, op2_12;
wire [6:0] op_cc_12;

always @(posedge clk) begin
halt <= haltedP;
end

//module stage0(PCfollow,ir,halt,R15,Z,clk,reset);
stage0 s0(PCfollow_01,ir,haltedP,16'h0000,1'b0,clk,reset);

//module stage1(pc_follow, op_cc_out, Rd_out, op2_out, ir, clk, reset, pc);
stage1 s1(PCfollow_12, op_cc_12, Rd_12, op2_12, ir, clk, reset, PCfollow_01);

always @(reset) begin
	halt = 0;
end

endmodule

module testbench;
reg reset = 0;
reg clk = 0;
wire halted;
processor PE(halted, reset, clk);
initial begin
  $dumpfile("dumpfile.vcd");
  $dumpvars(0,PE);
  #10 reset = 1;
  #10 reset = 0;
  while (!halted) begin
    #10 clk = 1;
    #10 clk = 0;
  end
  $finish;
end
endmodule

dumpfile.vcd
$date
	Tue Oct 30 15:43:22 2018
$end
$version
	Icarus Verilog
$end
$timescale
	1s
$end
$scope module testbench $end
$scope module PE $end
$var wire 1 ! clk $end
$var wire 1 " reset $end
$var wire 7 # op_cc_12 [6:0] $end
$var wire 16 $ op2_12 [15:0] $end
$var wire 16 % ir [15:0] $end
$var wire 1 & haltedP $end
$var wire 16 ' Rd_12 [15:0] $end
$var wire 16 ( PCfollow_12 [15:0] $end
$var wire 16 ) PCfollow_01 [15:0] $end
$var reg 1 * halt $end
$scope module s0 $end
$var wire 16 + R15 [15:0] $end
$var wire 1 , Z $end
$var wire 1 ! clk $end
$var wire 1 - insertNOP $end
$var wire 16 . irInitial [15:0] $end
$var wire 1 " reset $end
$var wire 16 / ir [15:0] $end
$var wire 1 & halt $end
$var wire 2 0 CC [1:0] $end
$var reg 16 1 PC [15:0] $end
$var reg 16 2 PCfollow [15:0] $end
$upscope $end
$scope module s1 $end
$var wire 16 3 Rd_out [15:0] $end
$var wire 1 ! clk $end
$var wire 16 4 ir [15:0] $end
$var wire 16 5 pc [15:0] $end
$var wire 1 " reset $end
$var wire 5 6 op_code [4:0] $end
$var wire 16 7 op2_out [15:0] $end
$var wire 1 8 immFlag $end
$var wire 2 9 cc [1:0] $end
$var wire 1 : Rd $end
$var reg 7 ; op_cc_out [6:0] $end
$var reg 16 < pc_follow [15:0] $end
$var reg 12 = pre [11:0] $end
$var reg 1 > preFlag $end
$upscope $end
$upscope $end
$upscope $end
$enddefinitions $end
#0
$dumpvars
0>
b0 =
bx <
bx ;
0:
b0 9
18
b0 7
b11000 6
bx 5
b1100000100100011 4
b0 3
bx 2
b0 1
b0 0
b1100000100100011 /
b1100000100100011 .
0-
0,
b0 +
0*
bx )
bx (
b0 '
0&
b1100000100100011 %
b0 $
bx #
0"
0!
$end
#10
1"
#20
0"
#30
b1001000110100 $
b1001000110100 7
1:
b0 6
b100010100 %
b100010100 /
b100010100 4
b100010100 .
b1 1
b0 )
b0 2
b0 5
b1100000 #
b1100000 ;
b100100011 =
1>
1!
#40
0!
#50
0:
b10100 6
08
b1010000000000000 %
b1010000000000000 /
b1010000000000000 4
b0 #
b0 ;
b0 (
b0 <
b1010000000000000 .
b10 1
b1 )
b1 2
b1 5
b0 $
b0 7
0>
1!
#60
0!
#70
b11 1
b10 )
b10 2
b10 5
b1010000 #
b1010000 ;
b1 (
b1 <
1!
#80
0!
#90
b10 (
b10 <
b100 1
b11 )
b11 2
b11 5
1!
#100
0!
#110
1&
b10011 6
b1001100000000000 %
b1001100000000000 /
b1001100000000000 4
b1001100000000000 .
b101 1
b100 )
b100 2
b100 5
b11 (
b11 <
1!
#120
0!
#130
bx $
bx 7
x-
bx '
bx 3
x:
x&
bx 6
bx 9
x8
bx 0
bx %
bx /
bx 4
1*
b1001100 #
b1001100 ;
b100 (
b100 <
bx .
b110 1
b101 )
b101 2
b101 5
1!
