pinkyCGI.v
//
`define INST_END_INDEX	5

//common bit lengths
`define WORD 		[15:0]
`define OPCODE 		[15:11]
`define CC			[10:9]
`define IMM			[8]
`define DEST		[7:4]
`define	OP2			[3:0]
`define REGS		[15:0]
`define PC			registers[15]
`define SIZE		[65535:0]
`define PRESIZE		[11:0]
`define BASEOPS		[3:0]

//stage 
`define	STAGE       [1:0]		
`define STAGE0		0
`define STAGE1		1
`define	STAGE2		2
`define STAGE3		3

//OPCODES
`define OPADD 	5'b00000
`define OPADDF 	5'b00001
`define OPAND	5'b00010
`define OPBIC	5'b00011
`define OPEOR	5'b00100
`define OPFTOI  5'b00101
`define OPITOF  5'b00110
`define OPLDR   5'b00111
`define OPMOV   5'b01000
`define OPMUL   5'b01001
`define OPMULF  5'b01010
`define OPNEG   5'b01011
`define OPORR   5'b01100
`define OPRECF  5'b01101
`define OPSHA   5'b01110
`define OPSTR   5'b01111
`define OPSLT   5'b10000
`define OPSUB   5'b10001
`define OPSUBF  5'b10010
`define OPSYS   5'b10011
`define OPNOP   5'b10100
//5'b10101
//5'b10110
//5'b10111
`define OPPRE   5'b11000


//CC values
`define	AL			0
`define S 			1
`define NE			2
`define EQ			3

//OP2 MACRO
`define Op2struct(IR, PRE, PREFLAG, REGFILE) \
	(IR `IMM ? { PREFLAG ? {IR `OP2, PRE} : {12{IR[3]}}, IR `OP2 } : REGFILE[IR `OP2] )

module stage0(PCfollow,ir,halt,R15,Z,clk,reset);
			  
output reg `WORD PCfollow;
output `WORD ir;
output halt;
input `WORD R15;
input Z,clk,reset;

reg `WORD instmem `SIZE;	
reg `WORD PC;				
wire `WORD irInitial;
wire checkCodes;
wire [1:0] CC;

always@(reset) begin
	PC = 0;
	$readmemh("inst.txt", instmem, 0, `INST_END_INDEX);
end

always@(posedge clk) begin
	PCfollow <= PC;
	PC <= PC + 1;
end

assign irInitial = instmem[PC];
assign CC = irInitial `CC;
assign insertNOP = ((CC == `NE)&&(Z == 1))||((CC == `EQ)&&(Z == 0));
assign ir = (insertNOP == 1)? {`OPNOP,11'h000} : instmem[PC];
assign halt = (ir `OPCODE == `OPSYS);

endmodule


module stage1(pc_follow, op_cc_out, Rd_out, op2_out, ir, clk, reset, pc);
output reg `WORD pc_follow;
output `WORD Rd_out, op2_out;
output reg [6:0] op_cc_out;
input `WORD ir;
input clk, reset;
input `WORD pc;

wire [4:0] op_code;
wire [1:0] cc;
wire immFlag;

reg `WORD regfile `REGS;
reg preFlag;
reg `PRESIZE pre, pre_temp;



always@(reset)begin
    $readmemh("regs.txt", regfile, 0, 15);
    preFlag = 0;
    pre = 0;

end

//split up instruction word into the separate chunks
assign op_code = ir `OPCODE;
assign cc = ir `CC;
assign immFlag = ir `IMM;
assign Rd = ir `DEST;
assign Rd_out = regfile[Rd];

//`define Op2struct(IR, PRE, PREFLAG, REGFILE) \
//	(IR `IMM ? { PREFLAG ? {PRE, IR `OP2} : {12{IR[3]}}, IR `OP2 } : REGFILE[IR `OP2] )
assign op2_out = (ir[15] & ir[14]) ? 16'h0000 :  `Op2struct(ir, pre, preFlag, regfile);

//assign pre = pre_temp;
//assign pre = (ir[15] & ir[14]) ? ir `PRESIZE : pre_temp;
//assign preFlag = ir[15] & ir[14];
//assign Rn = ir `OP2;

always@(posedge clk)begin
    if(ir[15] & ir[14]) 
	begin
	preFlag = 1;
	pre = ir `PRESIZE;
	end
    else if(immFlag) preFlag = 0;
    
    pc_follow <= pc;
    op_cc_out <= {op_code, cc};
    //Rd_out <= regfile[Rd];
    //op2_out <= (ir[15] & ir[14]) ? 16'h0000 :  `Op2struct(ir, pre, preFlag, regfile);
end
endmodule

module stage2(pc_follow, op_cc_out, value_out, op_cc_in, addr, data, clk, reset, pc);
output reg `WORD pc_follow, value_out;
output reg [6:0]  op_cc_out;
input `WORD addr, data, pc;
input clk, reset;
input [6:0] op_cc_in;
reg `WORD datamem `SIZE;

wire [4:0]op;
assign op = op_cc_in[6:2];

//do the ALU thing
//when comparing to the PinKY instruction set
//Rd is addr and Op2 is data

always@(reset)begin
    //only reading in 16 data mem locations for now
    $readmemh("data.txt", datamem, 0, 15);
end

always@(posedge clk)begin
    case(op)
        `OPADD : begin value_out <= addr + data; end
        `OPAND : begin value_out <= addr & data; end
        `OPBIC : begin value_out <= addr & ~data; end
        `OPEOR : begin value_out <= addr ^ data; end
        `OPLDR : begin value_out <= datamem[data]; end
        `OPMOV : begin value_out <= data; end
        `OPMUL : begin value_out <= addr * data; end
        `OPNEG : begin value_out <= -data; end
        `OPORR : begin value_out <= addr | data; end
        `OPSHA : begin value_out <= ((data>0) ? addr<<data : addr>>-data); end
        `OPSTR : begin value_out <= data; datamem[addr] = data; end
        `OPSLT : begin value_out <= (addr<data); end
        `OPSUB : begin value_out <= addr - data; end
    //we'll catch these in the default case
    //    `OPSYS : begin ; end
    //    `OPNOP : begin ; end
    //    `OPPRE : begin ; end
        default : begin value_out <= 16'h0000; end
    endcase

    pc_follow <= pc;
    op_cc_out <= op_cc_in;
end

endmodule


module processor(halt, reset, clk);
output reg halt;
input reset, clk;

//the underscore<digit><digit> notation indicates control flow
//for example _12 means it goes from stage 1 to stage 2
wire `WORD PCfollow_01, PCfollow_12, PCfollow_23, PCfollow_30;
wire `WORD ir;
wire haltedP;
wire `WORD Rd_12, op2_12;
wire [6:0] op_cc_12, op_cc_23;
wire `WORD result;

always @(posedge clk) begin
halt <= haltedP;
end

//module stage0(PCfollow,ir,halt,R15,Z,clk,reset);
stage0 s0(PCfollow_01,ir,haltedP,16'h0000,1'b0,clk,reset);

//module stage1(pc_follow, op_cc_out, Rd_out, op2_out, ir, clk, reset, pc);
stage1 s1(PCfollow_12, op_cc_12, Rd_12, op2_12, ir, clk, reset, PCfollow_01);

//module stage2(pc_follow, op_cc_out, value_out, op_cc_in, addr, data, clk, reset, pc);
stage2 s2(PCfollow_23, op_cc_23, result, op_cc_12, Rd_12, op2_12, clk, reset, PCfollow_12);

always @(reset) begin
	halt = 0;
end

endmodule

module testbench;
reg reset = 0;
reg clk = 0;
wire halted;
processor PE(halted, reset, clk);
initial begin
  $dumpfile("dumpfile.vcd");
  $dumpvars(0,PE);
  #10 reset = 1;
  #10 reset = 0;
  while (!halted) begin
    #10 clk = 1;
    #10 clk = 0;
  end
  $finish;
end
endmodule

dumpfile.vcd
$date
	Tue Oct 30 17:06:05 2018
$end
$version
	Icarus Verilog
$end
$timescale
	1s
$end
$scope module testbench $end
$scope module PE $end
$var wire 1 ! clk $end
$var wire 1 " reset $end
$var wire 16 # result [15:0] $end
$var wire 7 $ op_cc_23 [6:0] $end
$var wire 7 % op_cc_12 [6:0] $end
$var wire 16 & op2_12 [15:0] $end
$var wire 16 ' ir [15:0] $end
$var wire 1 ( haltedP $end
$var wire 16 ) Rd_12 [15:0] $end
$var wire 16 * PCfollow_23 [15:0] $end
$var wire 16 + PCfollow_12 [15:0] $end
$var wire 16 , PCfollow_01 [15:0] $end
$var reg 1 - halt $end
$scope module s0 $end
$var wire 16 . R15 [15:0] $end
$var wire 1 / Z $end
$var wire 1 ! clk $end
$var wire 1 0 insertNOP $end
$var wire 16 1 irInitial [15:0] $end
$var wire 1 " reset $end
$var wire 16 2 ir [15:0] $end
$var wire 1 ( halt $end
$var wire 2 3 CC [1:0] $end
$var reg 16 4 PC [15:0] $end
$var reg 16 5 PCfollow [15:0] $end
$upscope $end
$scope module s1 $end
$var wire 16 6 Rd_out [15:0] $end
$var wire 1 ! clk $end
$var wire 16 7 ir [15:0] $end
$var wire 16 8 pc [15:0] $end
$var wire 1 " reset $end
$var wire 5 9 op_code [4:0] $end
$var wire 16 : op2_out [15:0] $end
$var wire 1 ; immFlag $end
$var wire 2 < cc [1:0] $end
$var wire 1 = Rd $end
$var reg 7 > op_cc_out [6:0] $end
$var reg 16 ? pc_follow [15:0] $end
$var reg 12 @ pre [11:0] $end
$var reg 1 A preFlag $end
$upscope $end
$scope module s2 $end
$var wire 16 B addr [15:0] $end
$var wire 1 ! clk $end
$var wire 16 C data [15:0] $end
$var wire 7 D op_cc_in [6:0] $end
$var wire 16 E pc [15:0] $end
$var wire 1 " reset $end
$var wire 5 F op [4:0] $end
$var reg 7 G op_cc_out [6:0] $end
$var reg 16 H pc_follow [15:0] $end
$var reg 16 I value_out [15:0] $end
$upscope $end
$upscope $end
$upscope $end
$enddefinitions $end
#0
$dumpvars
bx I
bx H
bx G
bx F
bx E
bx D
b0 C
b0 B
0A
b0 @
bx ?
bx >
0=
b0 <
1;
b0 :
b11000 9
bx 8
b1100000100100011 7
b0 6
bx 5
b0 4
b0 3
b1100000100100011 2
b1100000100100011 1
00
0/
b0 .
0-
bx ,
bx +
bx *
b0 )
0(
b1100000100100011 '
b0 &
bx %
bx $
bx #
0"
0!
$end
#10
1"
#20
0"
#30
b1001000110100 &
b1001000110100 :
b1001000110100 C
1=
b0 9
b100010100 '
b100010100 2
b100010100 7
b11000 F
b100010100 1
b1 4
b0 ,
b0 5
b0 8
b1100000 %
b1100000 >
b1100000 D
b0 #
b0 I
b100100011 @
1A
1!
#40
0!
#50
0=
b10100 9
0;
b0 F
b1010000000000000 '
b1010000000000000 2
b1010000000000000 7
b1100000 $
b1100000 G
b0 %
b0 >
b0 D
b0 +
b0 ?
b0 E
b1010000000000000 1
b10 4
b1 ,
b1 5
b1 8
b0 &
b0 :
b0 C
0A
1!
#60
0!
#70
b10100 F
b11 4
b10 ,
b10 5
b10 8
b1010000 %
b1010000 >
b1010000 D
b1 +
b1 ?
b1 E
b0 $
b0 G
b0 *
b0 H
1!
#80
0!
#90
b1010000 $
b1010000 G
b1 *
b1 H
b10 +
b10 ?
b10 E
b100 4
b11 ,
b11 5
b11 8
1!
#100
0!
#110
1(
b10011 9
b1001100000000000 '
b1001100000000000 2
b1001100000000000 7
b1001100000000000 1
b101 4
b100 ,
b100 5
b100 8
b11 +
b11 ?
b11 E
b10 *
b10 H
1!
#120
0!
#130
bx &
bx :
bx C
x0
bx )
bx 6
bx B
x=
x(
bx 9
bx <
x;
b10011 F
bx 3
bx '
bx 2
bx 7
1-
b11 *
b11 H
b1001100 %
b1001100 >
b1001100 D
b100 +
b100 ?
b100 E
bx 1
b110 4
b101 ,
b101 5
b101 8
1!
